{
	"generator_info": "Shape definitions generated with PhysicsEditor. Visit https://www.codeandweb.com/physicseditor",
	"walls": {
		"type": "fromPhysicsEditor",
		"label": "walls",
		"isStatic": false,
		"density": 0.1,
		"restitution": 0,
		"friction": 0.1,
		"frictionAir": 0.01,
		"frictionStatic": 0.5,
		"collisionFilter": {
			"group": 0,
			"category": 1,
			"mask": 255
		},
		"fixtures": [
			{
				"label": "",
				"isSensor": false,
				"vertices": [
					[ { "x":1109, "y":579 }, { "x":1218, "y":628 }, { "x":1310, "y":628 }, { "x":1283, "y":499 }, { "x":1261, "y":443 }, { "x":1111, "y":497 } ],
					[ { "x":1312, "y":647 }, { "x":1310, "y":628 }, { "x":1218, "y":628 }, { "x":1302, "y":652 } ],
					[ { "x":753, "y":516 }, { "x":886, "y":450 }, { "x":328, "y":263 } ],
					[ { "x":1492, "y":638 }, { "x":1538, "y":633 }, { "x":1543, "y":-8 }, { "x":1462, "y":528 } ],
					[ { "x":1111, "y":497 }, { "x":1261, "y":443 }, { "x":1238, "y":424 }, { "x":619, "y":239 }, { "x":328, "y":263 }, { "x":886, "y":450 } ],
					[ { "x":1233, "y":320 }, { "x":1360, "y":348 }, { "x":1543, "y":-8 }, { "x":1135, "y":191 }, { "x":1196, "y":283 } ],
					[ { "x":1462, "y":528 }, { "x":1543, "y":-8 }, { "x":1417, "y":407 } ],
					[ { "x":1014, "y":257 }, { "x":905, "y":240 }, { "x":797, "y":233 }, { "x":619, "y":239 }, { "x":1134, "y":391 }, { "x":1044, "y":281 } ],
					[ { "x":275, "y":471 }, { "x":352, "y":483 }, { "x":366, "y":483 }, { "x":226, "y":193 }, { "x":202, "y":446 } ],
					[ { "x":1523, "y":649 }, { "x":1525, "y":953 }, { "x":1542, "y":974 }, { "x":1549, "y":646 } ],
					[ { "x":658, "y":462 }, { "x":328, "y":263 }, { "x":493, "y":450 } ],
					[ { "x":493, "y":450 }, { "x":328, "y":263 }, { "x":429, "y":460 } ],
					[ { "x":429, "y":460 }, { "x":328, "y":263 }, { "x":308, "y":259 }, { "x":366, "y":483 } ],
					[ { "x":308, "y":259 }, { "x":273, "y":237 }, { "x":366, "y":483 } ],
					[ { "x":273, "y":237 }, { "x":226, "y":193 }, { "x":366, "y":483 } ],
					[ { "x":1417, "y":407 }, { "x":1543, "y":-8 }, { "x":1396, "y":369 } ],
					[ { "x":1396, "y":369 }, { "x":1543, "y":-8 }, { "x":1360, "y":348 } ],
					[ { "x":1135, "y":191 }, { "x":1543, "y":-8 }, { "x":1114, "y":175 } ],
					[ { "x":1114, "y":175 }, { "x":1543, "y":-8 }, { "x":-5, "y":-15 }, { "x":742, "y":137 } ],
					[ { "x":742, "y":137 }, { "x":-5, "y":-15 }, { "x":388, "y":152 } ],
					[ { "x":388, "y":152 }, { "x":-5, "y":-15 }, { "x":233, "y":181 } ],
					[ { "x":202, "y":446 }, { "x":226, "y":193 }, { "x":164, "y":441 } ],
					[ { "x":164, "y":441 }, { "x":226, "y":193 }, { "x":107, "y":460 } ],
					[ { "x":107, "y":460 }, { "x":226, "y":193 }, { "x":227, "y":187 }, { "x":-5, "y":-15 }, { "x":10.526315689086914, "y":513.9473571777344 } ],
					[ { "x":233, "y":181 }, { "x":-5, "y":-15 }, { "x":227, "y":187 } ],
					[ { "x":-5, "y":-15 }, { "x":-14, "y":977 }, { "x":12, "y":952 } ],
					[ { "x":-14, "y":977 }, { "x":1542, "y":974 }, { "x":1525, "y":953 }, { "x":12, "y":952 } ]
				]
			},
			{
				"label": "",
				"isSensor": false,
				"vertices": [
					[ { "x":1562, "y":622 }, { "x":1522, "y":622 }, { "x":1522, "y":662 } ]
				]
			}
		]
	},
	"beacon": {
		"type": "fromPhysicsEditor",
		"label": "beacon",
		"isStatic": false,
		"density": 0.10000000149011612,
		"restitution": 0,
		"friction": 0.10000000149011612,
		"frictionAir": 0.009999999776482582,
		"frictionStatic": 0.5,
		"collisionFilter": {
			"group": 0,
			"category": 1,
			"mask": 255
		},
		"fixtures": [
			{
				"label": "",
				"isSensor": false,
				"vertices": [
					[ { "x":463, "y":280 }, { "x":367, "y":144 }, { "x":126, "y":179 }, { "x":229, "y":295 } ]
				]
			}
		]
	},
	"beach": {
		"type": "fromPhysicsEditor",
		"label": "beach",
		"isStatic": false,
		"density": 0.1,
		"restitution": 0,
		"friction": 0.1,
		"frictionAir": 0.01,
		"frictionStatic": 0.5,
		"collisionFilter": {
			"group": 0,
			"category": 1,
			"mask": 255
		},
		"fixtures": [
			{
				"label": "",
				"isSensor": false,
				"vertices": [
					[ { "x":406, "y":464 }, { "x":468, "y":531 }, { "x":613, "y":503 }, { "x":520, "y":444 } ]
				]
			}
		]
	},
	"drums": {
		"type": "fromPhysicsEditor",
		"label": "drums",
		"isStatic": false,
		"density": 0.10000000149011612,
		"restitution": 0,
		"friction": 0.10000000149011612,
		"frictionAir": 0.009999999776482582,
		"frictionStatic": 0.5,
		"collisionFilter": {
			"group": 0,
			"category": 1,
			"mask": 255
		},
		"fixtures": [
			{
				"label": "",
				"isSensor": false,
				"vertices": [
					[ { "x":68, "y":535 }, { "x":281, "y":534 }, { "x":284, "y":428 }, { "x":68, "y":427 } ]
				]
			}
		]
	}
}
